[{"id":1,"img":"../images/banner1.jpg","url":"https://activity.lenovo.com.cn/2019/1111.html?pmf_group=in-push&pmf_medium=banner-gw&pmf_source=Z00010998T002&_ga=2.89785883.1085071349.1573441755-471730661.1573441755"},{"id":2,"img":"../images/banner2.jpg","url":"https://activity.lenovo.com.cn/2019/1111.html?pmf_group=in-push&pmf_medium=banner-gw&pmf_source=Z00010998T002&_ga=2.89785883.1085071349.1573441755-471730661.1573441755"},{"id":3,"img":"../images/banner3.jpg","url":"https://activity.lenovo.com.cn/2019/1111.html?pmf_group=in-push&pmf_medium=banner-gw&pmf_source=Z00010998T002&_ga=2.89785883.1085071349.1573441755-471730661.1573441755"},{"id":4,"img":"../images/banner4.jpg","url":"https://activity.lenovo.com.cn/2019/1111.html?pmf_group=in-push&pmf_medium=banner-gw&pmf_source=Z00010998T002&_ga=2.89785883.1085071349.1573441755-471730661.1573441755"},{"id":5,"img":"../images/banner5.jpg","url":"https://activity.lenovo.com.cn/2019/1111.html?pmf_group=in-push&pmf_medium=banner-gw&pmf_source=Z00010998T002&_ga=2.89785883.1085071349.1573441755-471730661.1573441755"},{"id":6,"img":"../images/banner6.jpg","url":"https://activity.lenovo.com.cn/2019/1111.html?pmf_group=in-push&pmf_medium=banner-gw&pmf_source=Z00010998T002&_ga=2.89785883.1085071349.1573441755-471730661.1573441755"},{"id":7,"img":"../images/banner7.jpg","url":"https://activity.lenovo.com.cn/2019/1111.html?pmf_group=in-push&pmf_medium=banner-gw&pmf_source=Z00010998T002&_ga=2.89785883.1085071349.1573441755-471730661.1573441755"},{"id":8,"img":"../images/banner8.jpg","url":"https://activity.lenovo.com.cn/2019/1111.html?pmf_group=in-push&pmf_medium=banner-gw&pmf_source=Z00010998T002&_ga=2.89785883.1085071349.1573441755-471730661.1573441755"},{"id":1,"img":"../images/banner1.jpg","url":"https://activity.lenovo.com.cn/2019/1111.html?pmf_group=in-push&pmf_medium=banner-gw&pmf_source=Z00010998T002&_ga=2.89785883.1085071349.1573441755-471730661.1573441755"},{"id":9,"img":"../images/banner9.jpg","url":"https://activity.lenovo.com.cn/2019/1111.html?pmf_group=in-push&pmf_medium=banner-gw&pmf_source=Z00010998T002&_ga=2.89785883.1085071349.1573441755-471730661.1573441755"},{"id":10,"img":"../images/banner10.jpg","url":"https://activity.lenovo.com.cn/2019/1111.html?pmf_group=in-push&pmf_medium=banner-gw&pmf_source=Z00010998T002&_ga=2.89785883.1085071349.1573441755-471730661.1573441755"},{"id":11,"img":"../images/banner11.jpg","url":"https://activity.lenovo.com.cn/2019/1111.html?pmf_group=in-push&pmf_medium=banner-gw&pmf_source=Z00010998T002&_ga=2.89785883.1085071349.1573441755-471730661.1573441755"},{"id":12,"img":"../images/banner12.jpg","url":"https://activity.lenovo.com.cn/2019/1111.html?pmf_group=in-push&pmf_medium=banner-gw&pmf_source=Z00010998T002&_ga=2.89785883.1085071349.1573441755-471730661.1573441755"}]
